nonebot_plugin_shuiguola-0.1.3.dist-info/METADATA
nonebot_plugin_shuiguola-0.1.3.dist-info/WHEEL
nonebot_plugin_shuiguola/__init__.py
nonebot_plugin_shuiguola/config.py
nonebot_plugin_shuiguola/database.py
nonebot_plugin_shuiguola/shuiguole.jpg
nonebot_plugin_shuiguola/shuilanle.jpg
nonebot_plugin_shuiguola-0.1.3.dist-info/RECORD
